docker/novae/Dockerfile
novae/__init__.py
novae/_constants.py
novae/_logging.py
novae/_settings.py
novae/model.py
novae/data/__init__.py
novae/data/convert.py
novae/data/datamodule.py
novae/data/dataset.py
novae/data/preprocess.py
novae/data/_embeddings/__init__.py
novae/data/_embeddings/_histo.py
novae/data/_load/__init__.py
novae/data/_load/_hf.py
novae/data/_load/_toy.py
novae/data/_load/_wandb.py
novae/module/__init__.py
novae/module/aggregate.py
novae/module/augment.py
novae/module/embed.py
novae/module/encode.py
novae/module/swav.py
novae/monitor/__init__.py
novae/monitor/callback.py
novae/monitor/eval.py
novae/monitor/log.py
novae/plot/__init__.py
novae/plot/_bar.py
novae/plot/_graph.py
novae/plot/_heatmap.py
novae/plot/_line.py
novae/plot/_spatial.py
novae/plot/_utils.py
novae/utils/__init__.py
novae/utils/_utils.py
novae/utils/_validate.py
novae/utils/build.py
novae/utils/correct.py
novae/utils/mode.py
novae-1.0.2.dist-info/METADATA
novae-1.0.2.dist-info/WHEEL
novae-1.0.2.dist-info/licenses/LICENSE
novae-1.0.2.dist-info/RECORD
