Metadata-Version: 2.4
Name: novae
Version: 1.0.2
Summary: Graph-based foundation model for spatial transcriptomics data
Project-URL: Homepage, https://mics-lab.github.io/novae/
Project-URL: Repository, https://github.com/MICS-Lab/novae
Project-URL: Documentation, https://mics-lab.github.io/novae/
Author-email: Quentin Blampey <quentin.blampey@gmail.com>
License-Expression: BSD-3-Clause
License-File: LICENSE
Classifier: License :: OSI Approved :: BSD License
Classifier: Operating System :: MacOS :: MacOS X
Classifier: Operating System :: Microsoft :: Windows
Classifier: Operating System :: POSIX :: Linux
Classifier: Programming Language :: Python :: 3
Classifier: Topic :: Scientific/Engineering
Requires-Python: >=3.11
Requires-Dist: fast-array-utils>=1.3.1
Requires-Dist: huggingface-hub>=0.32.0
Requires-Dist: igraph>=0.11.8
Requires-Dist: lightning>=2.2.1
Requires-Dist: pandas>=2.0.0
Requires-Dist: safetensors>=0.4.3
Requires-Dist: scanpy>=1.9.8
Requires-Dist: torch-geometric>=2.5.2
Requires-Dist: torch>=2.2.1
Provides-Extra: conch
Requires-Dist: einops-exts>=0.0.4; extra == 'conch'
Requires-Dist: transformers>=4.52.4; extra == 'conch'
Provides-Extra: multimodal
Requires-Dist: sopa>=2.1.11; extra == 'multimodal'
Requires-Dist: timm>=1.0.15; extra == 'multimodal'
